giaola_xml_utils/__init__.py
giaola_xml_utils/cli.py
giaola_xml_utils/parsers.py
giaola_xml_utils-0.4.1.dist-info/DESCRIPTION.rst
giaola_xml_utils-0.4.1.dist-info/METADATA
giaola_xml_utils-0.4.1.dist-info/RECORD
giaola_xml_utils-0.4.1.dist-info/WHEEL
giaola_xml_utils-0.4.1.dist-info/entry_points.txt
giaola_xml_utils-0.4.1.dist-info/metadata.json
giaola_xml_utils-0.4.1.dist-info/top_level.txt
