Metadata-Version: 2.0
Name: giaola-xml-utils
Version: 0.4.1
Summary: XML utility functions
Home-page: https://github.com/g20ready/giaola_xml_utils
Author: Marsel Tzatzo
Author-email: tmarselg@gmail.com
License: MIT license
Keywords: giaola_xml_utils
Platform: UNKNOWN
Classifier: Development Status :: 2 - Pre-Alpha
Classifier: Intended Audience :: Developers
Classifier: License :: OSI Approved :: MIT License
Classifier: Natural Language :: English
Classifier: Programming Language :: Python :: 2
Classifier: Programming Language :: Python :: 2.6
Classifier: Programming Language :: Python :: 2.7
Classifier: Programming Language :: Python :: 3
Classifier: Programming Language :: Python :: 3.3
Classifier: Programming Language :: Python :: 3.4
Classifier: Programming Language :: Python :: 3.5
Requires-Dist: Click (>=6.0)
Requires-Dist: future (>=0.16.0)
Requires-Dist: lxml (>=3.0.0)
